dbfrs-0.1.5.dist-info/METADATA
dbfrs-0.1.5.dist-info/WHEEL
dbfrs/__init__.py
dbfrs/dbfrs.abi3.so
dbfrs-0.1.5.dist-info/RECORD
