Metadata-Version: 2.3
Name: dbfrs
Version: 0.1.5
Classifier: Programming Language :: Rust
Classifier: Programming Language :: Python :: Implementation :: CPython
Classifier: Programming Language :: Python :: Implementation :: PyPy
Author: Roland von Ohlen <crates@rvo.name>
Author-email: Roland von Ohlen <crates@rvo.name>
Requires-Python: >=3.10
